pywiface/__init__.py
pywiface/cli.py
pywiface/interface.py
pywiface/models.py
pywiface/threads.py
pywiface-0.2.1.dist-info/LICENSE
pywiface-0.2.1.dist-info/METADATA
pywiface-0.2.1.dist-info/WHEEL
pywiface-0.2.1.dist-info/entry_points.txt
pywiface-0.2.1.dist-info/top_level.txt
pywiface-0.2.1.dist-info/RECORD
