Metadata-Version: 2.1
Name: pywiface
Version: 0.2.1
Summary: Python wrapper for managing wireless interfaces
Home-page: UNKNOWN
Author: Keane O'Kelley
Author-email: keane.m.okelley@gmail.com
License: MIT
Platform: UNKNOWN
Requires-Dist: scapy-python3
Requires-Dist: termcolor
